<?xml version="1.0" encoding="UTF-8" standalone="no"?>
<bilans version="1.0" xmlns="fr:inpi:odrncs:bilansSaisisXML">
<bilan>
<identite>
<siren>379365208</siren>
<date_cloture_exercice>20180630</date_cloture_exercice>
<code_greffe>6201</code_greffe>
<num_depot>1949</num_depot>
<num_gestion>1997B00292</num_gestion>
<code_activite>6420Z</code_activite>
<date_cloture_exercice_n-1>20170630</date_cloture_exercice_n-1>
<duree_exercice_n>12</duree_exercice_n>
<duree_exercice_n-1>00</duree_exercice_n-1>
<date_depot>20190320</date_depot>
<code_motif>00</code_motif>
<code_type_bilan>C</code_type_bilan>
<code_devise>EUR</code_devise>
<code_origine_devise>O</code_origine_devise>
<code_confidentialite>0</code_confidentialite>
<info_traitement/>
<denomination><![CDATA[DBT]]></denomination>
<adresse><![CDATA[62117 BREBIERES]]></adresse>
</identite>
<detail>
<page numero="01">
<liasse code="AF" m1="000000000005086" m2="000000000002701" m3="000000000002385" m4="000000000004080"/>
<liasse code="AL" m1="000000000005000" m3="000000000005000"/>
<liasse code="CU" m1="000000013238909" m3="000000013238909" m4="000000010638909"/>
<liasse code="BH" m1="000000000040000" m3="000000000040000" m4="000000000120704"/>
<liasse code="BJ" m1="000000013288995" m2="000000000002701" m3="000000013286294" m4="000000010763690"/>
<liasse code="BX" m1="000000000072478" m3="000000000072478" m4="000000000229042"/>
<liasse code="BZ" m1="000000001997179" m3="000000001997179" m4="000000001281567"/>
<liasse code="CD" m1="000000000009660" m3="000000000009660" m4="000000000298785"/>
<liasse code="CF" m1="000000000216096" m3="000000000216096" m4="000000000110935"/>
<liasse code="CH" m4="000000000000334"/>
<liasse code="CJ" m1="000000002295413" m3="000000002295413" m4="000000001920662"/>
<liasse code="CO" m1="000000015584408" m2="000000000002701" m3="000000015581707" m4="000000012684355"/>
</page>
<page numero="02">
<liasse code="DA" m1="000000000648369" m2="000000000470657"/>
<liasse code="DB" m1="000000014116233" m2="000000010493946"/>
<liasse code="DD" m1="000000000026957" m2="000000000026957"/>
<liasse code="DF" m1="000000000556073" m2="000000000556073"/>
<liasse code="DH" m1="-000000001467426" m2="-000000000809040"/>
<liasse code="DI" m1="-000000000170040" m2="-000000000658385"/>
<liasse code="DJ" m2="000000000002610"/>
<liasse code="DL" m1="000000013710167" m2="000000010082817"/>
<liasse code="DS" m2="000000000200000"/>
<liasse code="DU" m1="000000000818892" m2="000000000820369"/>
<liasse code="DV" m1="000000000155899" m2="000000000344847"/>
<liasse code="DX" m1="000000000511013" m2="000000000941913"/>
<liasse code="DY" m1="000000000012343" m2="000000000192785"/>
<liasse code="EA" m1="000000000373924" m2="000000000102154"/>
<liasse code="EC" m1="000000001872071" m2="000000002602069"/>
<liasse code="ED" m1="-000000000000531" m2="-000000000000531"/>
<liasse code="EE" m1="000000015581707" m2="000000012684355"/>
<liasse code="EI" m1="000000000155899"/>
</page>
<page numero="03">
<liasse code="FG" m4="000000000165480"/>
<liasse code="FJ" m4="000000000165480"/>
<liasse code="FP" m4="000000000039363"/>
<liasse code="FQ" m3="000000000000556" m4="000000000000105"/>
<liasse code="FR" m3="000000000000556" m4="000000000204949"/>
<liasse code="FW" m3="000000000328032" m4="000000000717875"/>
<liasse code="FX" m3="000000000005724" m4="000000000046068"/>
<liasse code="FZ" m4="000000000001490"/>
<liasse code="GA" m3="000000000001695" m4="000000000001006"/>
<liasse code="GE" m3="000000000000011" m4="000000000000005"/>
<liasse code="GF" m3="000000000335462" m4="000000000766445"/>
<liasse code="GG" m3="-000000000334906" m4="-000000000561497"/>
<liasse code="GJ" m3="000000000042398" m4="000000000000748"/>
<liasse code="GK" m3="000000000024970" m4="000000000003730"/>
<liasse code="GL" m3="000000000125092" m4="000000000041000"/>
<liasse code="GM" m3="000000000002397" m4="000000000004710"/>
<liasse code="GO" m3="000000000010517" m4="000000000005381"/>
<liasse code="GP" m3="000000000205374" m4="000000000055569"/>
<liasse code="GR" m3="000000000043118" m4="000000000056689"/>
<liasse code="GU" m3="000000000043118" m4="000000000056689"/>
<liasse code="GV" m3="000000000162257" m4="-000000000001121"/>
<liasse code="GW" m3="-000000000172650" m4="-000000000562618"/>
</page>
<page numero="04">
<liasse code="HA" m2="000000000010001"/>
<liasse code="HB" m1="000000000002610" m2="000000000003480"/>
<liasse code="HD" m1="000000000002610" m2="000000000013481"/>
<liasse code="HF" m2="000000000109249"/>
<liasse code="HH" m2="000000000109249"/>
<liasse code="HI" m1="000000000002610" m2="-000000000095768"/>
<liasse code="HL" m1="000000000208540" m2="000000000273999"/>
<liasse code="HM" m1="000000000378580" m2="000000000932384"/>
<liasse code="HN" m1="-000000000170040" m2="-000000000658385"/>
</page>
<page numero="05">
<liasse code="KD" m1="000000000005086" m3="000000000005000"/>
<liasse code="LQ" m1="000000010762009" m3="000000002600000"/>
<liasse code="0G" m1="000000010767095" m3="000000002605000"/>
<liasse code="IO" m3="000000000010086"/>
<liasse code="I3" m2="000000000083101" m3="000000013278909"/>
<liasse code="I4" m2="000000000083101" m3="000000013288995"/>
</page>
<page numero="06">
<liasse code="PE" m1="000000000001006" m2="000000000001695" m4="000000000002701"/>
<liasse code="0N" m1="000000000001006" m2="000000000001695" m4="000000000002701"/>
</page>
<page numero="07">
<liasse code="06" m1="000000000002397" m3="000000000002397"/>
<liasse code="7B" m1="000000000002397" m3="000000000002397"/>
<liasse code="7C" m1="000000000002397" m3="000000000002397"/>
</page>
<page numero="08">
<liasse code="UT" m1="000000000040000" m3="000000000040000"/>
<liasse code="UX" m1="000000000072478" m2="000000000072478"/>
<liasse code="VB" m1="000000000167623" m2="000000000167623"/>
<liasse code="VC" m1="000000001821396" m2="000000001821396"/>
<liasse code="VR" m1="000000000008160" m2="000000000008160"/>
<liasse code="VT" m1="000000002109658" m2="000000002069658" m3="000000000040000"/>
<liasse code="VH" m1="000000000818892" m2="000000000368892" m3="000000000450000"/>
<liasse code="8A" m1="-000000000012100" m2="000000000155899" m3="-000000000168000"/>
<liasse code="8B" m1="000000000511013" m2="000000000511013"/>
<liasse code="VW" m1="000000000012080" m2="000000000012080"/>
<liasse code="VQ" m1="000000000000263" m2="000000000000263"/>
<liasse code="VI" m1="000000000168000" m2="000000000168000"/>
<liasse code="8K" m1="000000000373924" m2="000000000373924"/>
<liasse code="VY" m1="000000001872071" m2="000000001590071" m3="000000000282000"/>
</page>
</detail>
</bilan>
</bilans>
