<?xml version="1.0" encoding="UTF-8" standalone="no"?>
<bilans version="1.0" xmlns="fr:inpi:odrncs:bilansSaisisXML">
<bilan>
<identite>
<siren>512084625</siren>
<date_cloture_exercice>20180831</date_cloture_exercice>
<code_greffe>3801</code_greffe>
<num_depot>B2019/003541</num_depot>
<num_gestion>2009B00651</num_gestion>
<code_activite>9529Z</code_activite>
<date_cloture_exercice_n-1>20170831</date_cloture_exercice_n-1>
<duree_exercice_n>12</duree_exercice_n>
<duree_exercice_n-1>12</duree_exercice_n-1>
<date_depot>20190322</date_depot>
<code_motif>00</code_motif>
<code_type_bilan>S</code_type_bilan>
<code_devise>EUR</code_devise>
<code_origine_devise>O</code_origine_devise>
<code_confidentialite>0</code_confidentialite>
<info_traitement/>
<denomination><![CDATA[WINGSHOP]]></denomination>
<adresse><![CDATA[38660 SAINT HILAIRE]]></adresse>
</identite>
<detail>
<page numero="01">
<liasse code="010" m1="000000000009500" m3="000000000009500" m4="000000000009500"/>
<liasse code="014" m1="000000000000700" m2="000000000000700" m4="000000000000135"/>
<liasse code="028" m1="000000000039686" m2="000000000026377" m3="000000000013308" m4="000000000019131"/>
<liasse code="040" m1="000000000000400" m3="000000000000400" m4="000000000000400"/>
<liasse code="044" m1="000000000050286" m2="000000000027077" m3="000000000023208" m4="000000000029167"/>
<liasse code="050" m1="000000000014109" m2="000000000003038" m3="000000000011071" m4="000000000010234"/>
<liasse code="068" m1="000000000001322" m3="000000000001322" m4="000000000001428"/>
<liasse code="072" m1="000000000002417" m3="000000000002417" m4="000000000001564"/>
<liasse code="084" m1="000000000000464" m3="000000000000464"/>
<liasse code="092" m1="000000000001309" m3="000000000001309" m4="000000000000708"/>
<liasse code="096" m1="000000000019622" m2="000000000003038" m3="000000000016584" m4="000000000013935"/>
<liasse code="110" m1="000000000069908" m2="000000000030115" m3="000000000039792" m4="000000000043101"/>
<liasse code="120" m3="000000000006000" m4="000000000006000"/>
<liasse code="126" m3="000000000000600" m4="000000000000600"/>
<liasse code="132" m3="000000000028983" m4="000000000013742"/>
<liasse code="136" m3="000000000000253" m4="000000000015242"/>
<liasse code="142" m3="000000000035836" m4="000000000035583"/>
<liasse code="156" m4="000000000001979"/>
<liasse code="166" m3="000000000002850" m4="000000000002043"/>
<liasse code="169" m2="000000000000236"/>
<liasse code="172" m3="000000000001106" m4="000000000003497"/>
<liasse code="176" m3="000000000003956" m4="000000000007518"/>
<liasse code="180" m3="000000000039792" m4="000000000043101"/>
<liasse code="182" m3="000000000003694"/>
<liasse code="184" m3="000000000001667"/>
</page>
<page numero="02">
<liasse code="210" m1="000000000000208" m2="000000000004247"/>
<liasse code="218" m1="000000000107967" m2="000000000104492"/>
<liasse code="230" m1="000000000004713" m2="000000000000001"/>
<liasse code="232" m1="000000000112888" m2="000000000108741"/>
<liasse code="234" m1="000000000001197" m2="000000000003521"/>
<liasse code="238" m1="000000000004670" m2="000000000004182"/>
<liasse code="240" m1="000000000000449" m2="-000000000002801"/>
<liasse code="242" m1="000000000049542" m2="000000000045975"/>
<liasse code="243" m1="000000000000357"/>
<liasse code="244" m1="000000000005135" m2="000000000003889"/>
<liasse code="250" m1="000000000025650" m2="000000000022100"/>
<liasse code="252" m1="000000000014644" m2="000000000012831"/>
<liasse code="254" m1="000000000008693" m2="000000000005773"/>
<liasse code="256" m1="000000000003038" m2="000000000004323"/>
<liasse code="262" m1="000000000000002" m2="000000000000015"/>
<liasse code="264" m1="000000000113021" m2="000000000099807"/>
<liasse code="270" m1="-000000000000132" m2="000000000008933"/>
<liasse code="290" m1="000000000001667" m2="000000000010270"/>
<liasse code="294" m2="000000000000046"/>
<liasse code="300" m1="000000000000959" m2="000000000001000"/>
<liasse code="306" m1="000000000000322" m2="000000000002916"/>
<liasse code="310" m1="000000000000253" m2="000000000015242"/>
</page>
</detail>
</bilan>
</bilans>
