<?xml version="1.0" encoding="UTF-8" standalone="no"?>
<bilans version="1.0" xmlns="fr:inpi:odrncs:bilansSaisisXML">
<bilan>
<identite>
<siren>414596395</siren>
<date_cloture_exercice>20180630</date_cloture_exercice>
<code_greffe>6303</code_greffe>
<num_depot>2282</num_depot>
<num_gestion>2015D00362</num_gestion>
<code_activite>4773Z</code_activite>
<date_cloture_exercice_n-1>20170630</date_cloture_exercice_n-1>
<duree_exercice_n>12</duree_exercice_n>
<duree_exercice_n-1>12</duree_exercice_n-1>
<date_depot>20190322</date_depot>
<code_motif>1A</code_motif>
<code_type_bilan>C</code_type_bilan>
<code_devise>EUR</code_devise>
<code_origine_devise>O</code_origine_devise>
<code_confidentialite>0</code_confidentialite>
<info_traitement/>
<denomination><![CDATA[PHARMACIE DU LAC]]></denomination>
<adresse><![CDATA[63800 COURNON D AUVERGNE]]></adresse>
</identite>
<detail>
<page numero="01">
<liasse code="AF" m1="000000000000690" m2="000000000000690"/>
<liasse code="AH" m1="000000001966592" m3="000000001966592"/>
<liasse code="AR" m1="000000000004683" m2="000000000004593" m3="000000000000090"/>
<liasse code="AT" m1="000000000259522" m2="000000000158965" m3="000000000100556"/>
<liasse code="AX" m2="000000000000001"/>
<liasse code="CU" m1="000000000001001" m3="000000000001001"/>
<liasse code="BH" m1="000000000000820" m3="000000000000820"/>
<liasse code="BJ" m1="000000002233309" m2="000000000164248" m3="000000002069060"/>
<liasse code="BT" m1="000000000237994" m3="000000000237994"/>
<liasse code="BX" m1="000000000036650" m3="000000000036650"/>
<liasse code="BZ" m1="000000000301472" m3="000000000301472"/>
<liasse code="CF" m1="000000000198133" m3="000000000198133"/>
<liasse code="CH" m1="000000000013558" m3="000000000013558"/>
<liasse code="CJ" m1="000000000787808" m3="000000000787808"/>
<liasse code="CO" m1="000000003021118" m2="000000000164248" m3="000000002856869"/>
</page>
<page numero="02">
<liasse code="DA" m1="000000002218133"/>
<liasse code="DD" m1="000000000018456"/>
<liasse code="DG" m1="000000000000017"/>
<liasse code="DI" m1="000000000160444"/>
<liasse code="DL" m1="000000002397051"/>
<liasse code="DU" m1="000000000083448"/>
<liasse code="DV" m1="000000000071164"/>
<liasse code="DX" m1="000000000241392"/>
<liasse code="DY" m1="000000000063812"/>
<liasse code="EC" m1="000000000459818"/>
<liasse code="EE" m1="000000002856869"/>
<liasse code="EG" m1="000000000384855"/>
</page>
<page numero="03">
<liasse code="FA" m1="000000002580803" m3="000000002580803"/>
<liasse code="FG" m1="000000000068857" m3="000000000068857"/>
<liasse code="FJ" m1="000000002649661" m3="000000002649661"/>
<liasse code="FP" m3="000000000003586"/>
<liasse code="FQ" m3="000000000000017"/>
<liasse code="FR" m3="000000002653265"/>
<liasse code="FS" m3="000000001778748"/>
<liasse code="FT" m3="000000000034835"/>
<liasse code="FW" m3="000000000106737"/>
<liasse code="FX" m3="000000000009533"/>
<liasse code="FY" m3="000000000336909"/>
<liasse code="FZ" m3="000000000150508"/>
<liasse code="GA" m3="000000000016998"/>
<liasse code="GE" m3="000000000000011"/>
<liasse code="GF" m3="000000002434282"/>
<liasse code="GG" m3="000000000218982"/>
<liasse code="GL" m3="000000000003670"/>
<liasse code="GP" m3="000000000003670"/>
<liasse code="GR" m3="000000000000796"/>
<liasse code="GU" m3="000000000000796"/>
<liasse code="GV" m3="000000000002873"/>
<liasse code="GW" m3="000000000221855"/>
</page>
<page numero="04">
<liasse code="HE" m1="000000000000357"/>
<liasse code="HH" m1="000000000000357"/>
<liasse code="HI" m1="-000000000000357"/>
<liasse code="HK" m1="000000000061054"/>
<liasse code="HL" m1="000000002656935"/>
<liasse code="HM" m1="000000002496491"/>
<liasse code="HN" m1="000000000160444"/>
<liasse code="A1" m1="000000000003586"/>
<liasse code="A2" m1="000000000073917"/>
</page>
<page numero="05">
<liasse code="KD" m1="000000000000690"/>
<liasse code="LN" m1="000000000247668"/>
<liasse code="LQ" m1="000000000001822"/>
<liasse code="0G" m1="000000002216772"/>
<liasse code="IO" m3="000000000000690"/>
<liasse code="IY" m3="000000000264206"/>
<liasse code="I3" m3="000000000001822"/>
<liasse code="I4" m3="000000002233309"/>
</page>
<page numero="06">
<liasse code="PE" m1="000000000000128" m2="000000000000562" m4="000000000000690"/>
<liasse code="QU" m1="000000000147122" m2="000000000016437" m4="000000000163559"/>
<liasse code="0N" m1="000000000147250" m2="000000000016999" m4="000000000164249"/>
</page>
<page numero="08">
<liasse code="UT" m1="000000000000820" m3="000000000000820"/>
<liasse code="UX" m1="000000000036650" m2="000000000036650"/>
<liasse code="VP" m1="000000000301473" m2="000000000301473"/>
<liasse code="VS" m1="000000000013558" m2="000000000013558"/>
<liasse code="VT" m1="000000000352501" m2="000000000351681" m3="000000000000820"/>
<liasse code="VH" m1="000000000083448" m2="000000000008486" m3="000000000046227" m4="000000000028736"/>
<liasse code="8A" m1="000000000000160" m2="000000000000160"/>
<liasse code="8B" m1="000000000241393" m2="000000000241393"/>
<liasse code="VQ" m1="000000000063813" m2="000000000063813"/>
<liasse code="8K" m1="000000000071005" m2="000000000071005"/>
<liasse code="VY" m1="000000000459818" m2="000000000384856" m3="000000000046227" m4="000000000028736"/>
<liasse code="VK" m1="000000000011227"/>
</page>
</detail>
</bilan>
</bilans>
