<?xml version="1.0" encoding="UTF-8" standalone="no"?>
<bilans version="1.0" xmlns="fr:inpi:odrncs:bilansSaisisXML">
<bilan>
<identite>
<siren>537828790</siren>
<date_cloture_exercice>20180630</date_cloture_exercice>
<code_greffe>3802</code_greffe>
<num_depot>B2019/001821</num_depot>
<num_gestion>2011B01233</num_gestion>
<code_activite>3312Z</code_activite>
<date_cloture_exercice_n-1>20170630</date_cloture_exercice_n-1>
<duree_exercice_n>12</duree_exercice_n>
<duree_exercice_n-1>12</duree_exercice_n-1>
<date_depot>20190322</date_depot>
<code_motif>00</code_motif>
<code_type_bilan>C</code_type_bilan>
<code_devise>EUR</code_devise>
<code_origine_devise>O</code_origine_devise>
<code_confidentialite>0</code_confidentialite>
<info_traitement/>
<denomination><![CDATA[JB EMBALLAGE]]></denomination>
<adresse><![CDATA[38490 LES ABRETS-EN-DAUPHINE]]></adresse>
</identite>
<detail>
<page numero="01">
<liasse code="AR" m1="000000000015047" m2="000000000007900" m3="000000000007148" m4="000000000002959"/>
<liasse code="AT" m1="000000000028606" m2="000000000011864" m3="000000000016742" m4="000000000042263"/>
<liasse code="BH" m1="000000000000049" m3="000000000000049" m4="000000000000049"/>
<liasse code="BJ" m1="000000000043702" m2="000000000019764" m3="000000000023938" m4="000000000045271"/>
<liasse code="BL" m1="000000000006150" m3="000000000006150" m4="000000000005770"/>
<liasse code="BX" m1="000000000079682" m3="000000000079682" m4="000000000061762"/>
<liasse code="BZ" m1="000000000006156" m3="000000000006156" m4="000000000004808"/>
<liasse code="CF" m1="000000000033305" m3="000000000033305" m4="000000000027371"/>
<liasse code="CJ" m1="000000000125293" m3="000000000125293" m4="000000000099712"/>
<liasse code="CO" m1="000000000168995" m2="000000000019764" m3="000000000149231" m4="000000000144983"/>
</page>
<page numero="02">
<liasse code="DA" m1="000000000009000" m2="000000000009000"/>
<liasse code="DD" m1="000000000000900" m2="000000000000900"/>
<liasse code="DG" m1="000000000053034" m2="000000000061916"/>
<liasse code="DI" m1="000000000011667" m2="-000000000008883"/>
<liasse code="DL" m1="000000000074601" m2="000000000062934"/>
<liasse code="DT" m1="000000000023342" m2="000000000033202"/>
<liasse code="DV" m1="000000000000213" m2="000000000000504"/>
<liasse code="DX" m1="000000000029588" m2="000000000030725"/>
<liasse code="DY" m1="000000000019057" m2="000000000017402"/>
<liasse code="EA" m1="000000000002431" m2="000000000000216"/>
<liasse code="EC" m1="000000000074630" m2="000000000082048"/>
<liasse code="EE" m1="000000000149231" m2="000000000144982"/>
</page>
<page numero="03">
<liasse code="FD" m3="000000000253622" m4="000000000230991"/>
<liasse code="FJ" m3="000000000253622" m4="000000000230991"/>
<liasse code="FQ" m4="000000000001517"/>
<liasse code="FR" m3="000000000253622" m4="000000000232508"/>
<liasse code="FU" m3="000000000054567" m4="000000000067211"/>
<liasse code="FV" m3="-000000000000380" m4="-000000000004770"/>
<liasse code="FW" m3="000000000076915" m4="000000000086781"/>
<liasse code="FX" m3="000000000002701" m4="000000000001438"/>
<liasse code="FY" m3="000000000093568" m4="000000000076434"/>
<liasse code="GA" m3="000000000006559" m4="000000000009089"/>
<liasse code="GE" m4="000000000000053"/>
<liasse code="GF" m3="000000000233931" m4="000000000236236"/>
<liasse code="GG" m3="000000000019691" m4="-000000000003728"/>
<liasse code="GP" m3="000000000000001" m4="000000000000001"/>
<liasse code="GU" m3="000000000000739" m4="000000000000661"/>
<liasse code="GV" m3="-000000000000739" m4="-000000000000660"/>
<liasse code="GW" m3="000000000018952" m4="-000000000004388"/>
</page>
<page numero="04">
<liasse code="HD" m1="000000000022200" m2="000000000015000"/>
<liasse code="HH" m1="000000000027176" m2="000000000019494"/>
<liasse code="HI" m1="-000000000004976" m2="-000000000004494"/>
<liasse code="HK" m1="000000000002310"/>
<liasse code="HL" m1="000000000275823" m2="000000000247509"/>
<liasse code="HM" m1="000000000264156" m2="000000000256391"/>
<liasse code="HN" m1="000000000011667" m2="-000000000008883"/>
</page>
</detail>
</bilan>
</bilans>
