<?xml version="1.0" encoding="UTF-8" standalone="no"?>
<bilans version="1.0" xmlns="fr:inpi:odrncs:bilansSaisisXML">
<bilan>
<identite>
<siren>491670162</siren>
<date_cloture_exercice>20180331</date_cloture_exercice>
<code_greffe>5952</code_greffe>
<num_depot>775</num_depot>
<num_gestion>2006B50168</num_gestion>
<code_activite>9329Z</code_activite>
<date_cloture_exercice_n-1>20170331</date_cloture_exercice_n-1>
<duree_exercice_n>12</duree_exercice_n>
<duree_exercice_n-1>12</duree_exercice_n-1>
<date_depot>20190321</date_depot>
<code_motif>00</code_motif>
<code_type_bilan>C</code_type_bilan>
<code_devise>EUR</code_devise>
<code_origine_devise>O</code_origine_devise>
<code_confidentialite>0</code_confidentialite>
<info_traitement/>
<denomination><![CDATA[LE CLOS SAINT PIERRE]]></denomination>
<adresse><![CDATA[59360 BAZUEL]]></adresse>
</identite>
<detail>
<page numero="01">
<liasse code="AH" m1="000000000015000" m3="000000000015000" m4="000000000015000"/>
<liasse code="AN" m1="000000000014700" m3="000000000014700" m4="000000000014700"/>
<liasse code="AP" m1="000000000132300" m2="000000000054868" m3="000000000077432" m4="000000000084047"/>
<liasse code="AR" m1="000000000050502" m2="000000000050368" m3="000000000000134" m4="000000000000258"/>
<liasse code="AT" m1="000000000144289" m2="000000000143975" m3="000000000000314" m4="000000000004073"/>
<liasse code="BJ" m1="000000000356791" m2="000000000249211" m3="000000000107580" m4="000000000118078"/>
<liasse code="BT" m1="000000000003700" m3="000000000003700" m4="000000000003662"/>
<liasse code="BZ" m1="000000000050799" m3="000000000050799" m4="000000000051586"/>
<liasse code="CF" m1="000000000014771" m3="000000000014771" m4="000000000019651"/>
<liasse code="CH" m1="000000000001044" m3="000000000001044" m4="000000000000410"/>
<liasse code="CJ" m1="000000000070314" m3="000000000070314" m4="000000000075309"/>
<liasse code="CO" m1="000000000427105" m2="000000000249211" m3="000000000177894" m4="000000000193387"/>
</page>
<page numero="02">
<liasse code="DA" m1="000000000008000" m2="000000000008000"/>
<liasse code="DD" m1="000000000000800" m2="000000000000800"/>
<liasse code="DG" m1="000000000083037" m2="000000000067519"/>
<liasse code="DI" m1="000000000002551" m2="000000000015518"/>
<liasse code="DL" m1="000000000094388" m2="000000000091837"/>
<liasse code="DU" m1="000000000013629" m2="000000000031169"/>
<liasse code="DV" m1="000000000008135" m2="000000000008152"/>
<liasse code="DX" m1="000000000025066" m2="000000000022599"/>
<liasse code="DY" m1="000000000020501" m2="000000000023455"/>
<liasse code="EA" m1="000000000016175" m2="000000000016175"/>
<liasse code="EC" m1="000000000083506" m2="000000000101550"/>
<liasse code="EE" m1="000000000177894" m2="000000000193387"/>
<liasse code="EG" m1="000000000083506" m2="000000000101550"/>
</page>
<page numero="03">
<liasse code="FA" m1="000000000198663" m3="000000000198663" m4="000000000238055"/>
<liasse code="FG" m1="000000000003698" m3="000000000003698" m4="000000000003624"/>
<liasse code="FJ" m1="000000000202361" m3="000000000202361" m4="000000000241679"/>
<liasse code="FO" m4="000000000000281"/>
<liasse code="FQ" m3="000000000000001" m4="000000000000003"/>
<liasse code="FR" m3="000000000202362" m4="000000000241963"/>
<liasse code="FS" m3="000000000033530" m4="000000000041363"/>
<liasse code="FT" m3="-000000000000038" m4="-000000000000590"/>
<liasse code="FU" m3="000000000000102" m4="000000000000241"/>
<liasse code="FW" m3="000000000078053" m4="000000000084598"/>
<liasse code="FX" m3="000000000026820" m4="000000000029644"/>
<liasse code="FY" m3="000000000047551" m4="000000000048765"/>
<liasse code="FZ" m3="000000000001992" m4="000000000002507"/>
<liasse code="GA" m3="000000000010498" m4="000000000015314"/>
<liasse code="GE" m3="000000000000003" m4="000000000000033"/>
<liasse code="GF" m3="000000000198511" m4="000000000221875"/>
<liasse code="GG" m3="000000000003851" m4="000000000020088"/>
<liasse code="GL" m3="000000000000679" m4="000000000000872"/>
<liasse code="GP" m3="000000000000679" m4="000000000000872"/>
<liasse code="GR" m3="000000000001681" m4="000000000002581"/>
<liasse code="GU" m3="000000000001681" m4="000000000002581"/>
<liasse code="GV" m3="-000000000001002" m4="-000000000001708"/>
<liasse code="GW" m3="000000000002849" m4="000000000018380"/>
</page>
<page numero="04">
<liasse code="HE" m1="000000000000177" m2="000000000000500"/>
<liasse code="HH" m1="000000000000177" m2="000000000000500"/>
<liasse code="HI" m1="-000000000000177" m2="-000000000000500"/>
<liasse code="HK" m1="000000000000121" m2="000000000002362"/>
<liasse code="HL" m1="000000000203041" m2="000000000242836"/>
<liasse code="HM" m1="000000000200490" m2="000000000227318"/>
<liasse code="HN" m1="000000000002551" m2="000000000015518"/>
</page>
<page numero="05">
<liasse code="KD" m1="000000000015000"/>
<liasse code="LN" m1="000000000341791"/>
<liasse code="0G" m1="000000000356791"/>
<liasse code="IO" m3="000000000015000"/>
<liasse code="IY" m3="000000000341791"/>
<liasse code="I4" m3="000000000356791"/>
</page>
<page numero="06">
<liasse code="QU" m1="000000000238713" m2="000000000010498" m4="000000000249211"/>
<liasse code="0N" m1="000000000238713" m2="000000000010498" m4="000000000249211"/>
</page>
<page numero="08">
<liasse code="VM" m1="000000000002158" m2="000000000002158"/>
<liasse code="VB" m1="000000000003427" m2="000000000003427"/>
<liasse code="VP" m1="000000000000432" m2="000000000000432"/>
<liasse code="VC" m1="000000000041897" m2="000000000041897"/>
<liasse code="VR" m1="000000000002885" m2="000000000002885"/>
<liasse code="VS" m1="000000000001044" m2="000000000001044"/>
<liasse code="VT" m1="000000000051843" m2="000000000051843"/>
<liasse code="VH" m1="000000000013629" m2="000000000013629"/>
<liasse code="8B" m1="000000000025066" m2="000000000025066"/>
<liasse code="8C" m1="000000000004800" m2="000000000004800"/>
<liasse code="8D" m1="000000000008842" m2="000000000008842"/>
<liasse code="8E" m1="000000000000121" m2="000000000000121"/>
<liasse code="VW" m1="000000000005122" m2="000000000005122"/>
<liasse code="VQ" m1="000000000001617" m2="000000000001617"/>
<liasse code="VI" m1="000000000008135" m2="000000000008135"/>
<liasse code="8K" m1="000000000016175" m2="000000000016175"/>
<liasse code="VY" m1="000000000083506" m2="000000000083506"/>
<liasse code="VJ" m1="000000000032850"/>
<liasse code="VK" m1="000000000050269"/>
</page>
</detail>
</bilan>
</bilans>
