<?xml version="1.0" encoding="UTF-8" standalone="no"?>
<bilans version="1.0" xmlns="fr:inpi:odrncs:bilansSaisisXML">
<bilan>
<identite>
<siren>520824517</siren>
<date_cloture_exercice>20180630</date_cloture_exercice>
<code_greffe>3102</code_greffe>
<num_depot>B2019/005735</num_depot>
<num_gestion>2010B00904</num_gestion>
<code_activite>3511Z</code_activite>
<date_cloture_exercice_n-1>20170630</date_cloture_exercice_n-1>
<duree_exercice_n>12</duree_exercice_n>
<duree_exercice_n-1>12</duree_exercice_n-1>
<date_depot>20190320</date_depot>
<code_motif>00</code_motif>
<code_type_bilan>S</code_type_bilan>
<code_devise>EUR</code_devise>
<code_origine_devise>O</code_origine_devise>
<code_confidentialite>0</code_confidentialite>
<info_traitement/>
<denomination><![CDATA[EDROBAL]]></denomination>
<adresse><![CDATA[31660 BESSIERES]]></adresse>
</identite>
<detail>
<page numero="01">
<liasse code="028" m1="000000000110175" m2="000000000044315" m3="000000000065860" m4="000000000071369"/>
<liasse code="044" m1="000000000110175" m2="000000000044315" m3="000000000065860" m4="000000000071369"/>
<liasse code="072" m1="000000000000139" m3="000000000000139" m4="000000000000139"/>
<liasse code="080" m1="000000000000159" m3="000000000000159" m4="000000000000159"/>
<liasse code="084" m1="000000000017442" m3="000000000017442" m4="000000000014900"/>
<liasse code="092" m1="000000000000305" m3="000000000000305" m4="000000000000256"/>
<liasse code="096" m1="000000000018045" m3="000000000018045" m4="000000000015454"/>
<liasse code="110" m1="000000000128220" m2="000000000044315" m3="000000000083905" m4="000000000086823"/>
<liasse code="120" m3="000000000002000" m4="000000000002000"/>
<liasse code="134" m3="000000000000310" m4="-000000000000949"/>
<liasse code="136" m3="000000000000029" m4="000000000001258"/>
<liasse code="142" m3="000000000002339" m4="000000000002310"/>
<liasse code="156" m3="000000000036122" m4="000000000047401"/>
<liasse code="166" m3="000000000001020" m4="000000000000665"/>
<liasse code="169" m2="000000000044419"/>
<liasse code="172" m3="000000000044424" m4="000000000036446"/>
<liasse code="176" m3="000000000081566" m4="000000000084513"/>
<liasse code="180" m3="000000000083905" m4="000000000086823"/>
<liasse code="195" m3="000000000023698"/>
</page>
<page numero="02">
<liasse code="210" m1="000000000002220" m2="000000000005028"/>
<liasse code="218" m1="000000000016986" m2="000000000017137"/>
<liasse code="230" m2="000000000000001"/>
<liasse code="232" m1="000000000019206" m2="000000000022165"/>
<liasse code="234" m1="000000000000840" m2="000000000001949"/>
<liasse code="242" m1="000000000011313" m2="000000000011842"/>
<liasse code="243" m1="000000000000353"/>
<liasse code="244" m1="000000000000353" m2="000000000000349"/>
<liasse code="254" m1="000000000005509" m2="000000000005509"/>
<liasse code="262" m2="000000000000001"/>
<liasse code="264" m1="000000000018015" m2="000000000019649"/>
<liasse code="270" m1="000000000001191" m2="000000000002516"/>
<liasse code="280" m1="000000000000002" m2="000000000000002"/>
<liasse code="290" m2="000000000000325"/>
<liasse code="294" m1="000000000001159" m2="000000000001520"/>
<liasse code="306" m1="000000000000005" m2="000000000000066"/>
<liasse code="310" m1="000000000000029" m2="000000000001258"/>
</page>
<page numero="03">
<liasse code="490" m1="000000000110175"/>
</page>
</detail>
</bilan>
</bilans>
