<?xml version="1.0" encoding="UTF-8" standalone="no"?>
<bilans version="1.0" xmlns="fr:inpi:odrncs:bilansSaisisXML">
<bilan>
<identite>
<siren>519133052</siren>
<date_cloture_exercice>20171231</date_cloture_exercice>
<code_greffe>7608</code_greffe>
<num_depot>1879</num_depot>
<num_gestion>2009B01285</num_gestion>
<code_activite>4520A</code_activite>
<date_cloture_exercice_n-1>20161231</date_cloture_exercice_n-1>
<duree_exercice_n>12</duree_exercice_n>
<duree_exercice_n-1>12</duree_exercice_n-1>
<date_depot>20190321</date_depot>
<code_motif>00</code_motif>
<code_type_bilan>C</code_type_bilan>
<code_devise>EUR</code_devise>
<code_origine_devise>O</code_origine_devise>
<code_confidentialite>0</code_confidentialite>
<info_traitement/>
<denomination><![CDATA[SARL AUTO PASSION]]></denomination>
<adresse><![CDATA[76160 DARNETAL]]></adresse>
</identite>
<detail>
<page numero="01">
<liasse code="AH" m1="000000000116000" m3="000000000116000" m4="000000000116000"/>
<liasse code="AJ" m1="000000000002830" m2="000000000002830"/>
<liasse code="AR" m1="000000000027590" m2="000000000025723" m3="000000000001867" m4="000000000003012"/>
<liasse code="AT" m1="000000000000650" m2="000000000000650"/>
<liasse code="BJ" m1="000000000147070" m2="000000000029203" m3="000000000117867" m4="000000000119012"/>
<liasse code="BL" m1="000000000010002" m3="000000000010002" m4="000000000005069"/>
<liasse code="BN" m1="000000000002351" m3="000000000002351" m4="000000000002427"/>
<liasse code="BT" m1="000000000003906" m3="000000000003906" m4="000000000003776"/>
<liasse code="BX" m1="000000000054050" m3="000000000054050" m4="000000000067722"/>
<liasse code="BZ" m1="000000000046598" m3="000000000046598" m4="000000000034883"/>
<liasse code="CF" m1="000000000000424" m3="000000000000424" m4="000000000000395"/>
<liasse code="CH" m1="000000000002073" m3="000000000002073" m4="000000000000994"/>
<liasse code="CJ" m1="000000000119406" m3="000000000119406" m4="000000000115268"/>
<liasse code="CO" m1="000000000266476" m2="000000000029203" m3="000000000237273" m4="000000000234281"/>
</page>
<page numero="02">
<liasse code="DA" m1="000000000008000" m2="000000000008000"/>
<liasse code="DD" m1="000000000000800" m2="000000000000800"/>
<liasse code="DG" m1="000000000017905" m2="000000000043479"/>
<liasse code="DI" m1="000000000017566" m2="-000000000025574"/>
<liasse code="DL" m1="000000000044271" m2="000000000026706"/>
<liasse code="DU" m1="000000000030994" m2="000000000040422"/>
<liasse code="DV" m1="000000000083277" m2="000000000075677"/>
<liasse code="DW" m2="000000000000266"/>
<liasse code="DX" m1="000000000057788" m2="000000000060612"/>
<liasse code="DY" m1="000000000017428" m2="000000000027468"/>
<liasse code="EA" m1="000000000003514" m2="000000000003131"/>
<liasse code="EC" m1="000000000193002" m2="000000000207576"/>
<liasse code="EE" m1="000000000237273" m2="000000000234282"/>
<liasse code="EG" m1="000000000143002" m2="000000000157576"/>
</page>
<page numero="03">
<liasse code="FA" m1="000000000217407" m3="000000000217407" m4="000000000207218"/>
<liasse code="FG" m1="000000000219798" m3="000000000219798" m4="000000000190521"/>
<liasse code="FJ" m1="000000000437205" m3="000000000437205" m4="000000000397740"/>
<liasse code="FM" m3="-000000000000076" m4="000000000000352"/>
<liasse code="FO" m4="000000000001000"/>
<liasse code="FP" m3="000000000002181" m4="000000000002598"/>
<liasse code="FQ" m3="000000000000069" m4="000000000000140"/>
<liasse code="FR" m3="000000000439380" m4="000000000401832"/>
<liasse code="FS" m3="000000000154260" m4="000000000153699"/>
<liasse code="FT" m3="-000000000000129" m4="000000000001451"/>
<liasse code="FU" m3="000000000056394" m4="000000000062934"/>
<liasse code="FV" m3="-000000000004932" m4="000000000001938"/>
<liasse code="FW" m3="000000000099703" m4="000000000087947"/>
<liasse code="FX" m3="000000000002498" m4="000000000002747"/>
<liasse code="FY" m3="000000000099972" m4="000000000101951"/>
<liasse code="FZ" m3="000000000009272" m4="000000000009072"/>
<liasse code="GA" m3="000000000001144" m4="000000000002131"/>
<liasse code="GE" m3="000000000001712" m4="000000000000353"/>
<liasse code="GF" m3="000000000419898" m4="000000000424226"/>
<liasse code="GG" m3="000000000019482" m4="-000000000022394"/>
<liasse code="GR" m3="000000000002990" m4="000000000003618"/>
<liasse code="GU" m3="000000000002990" m4="000000000003618"/>
<liasse code="GV" m3="-000000000002990" m4="-000000000003618"/>
<liasse code="GW" m3="000000000016492" m4="-000000000026012"/>
</page>
<page numero="04">
<liasse code="HA" m1="000000000000618"/>
<liasse code="HB" m1="000000000000755"/>
<liasse code="HD" m1="000000000001373"/>
<liasse code="HE" m1="000000000000300" m2="000000000000022"/>
<liasse code="HH" m1="000000000000300" m2="000000000000022"/>
<liasse code="HI" m1="000000000001073" m2="-000000000000022"/>
<liasse code="HK" m2="-000000000000461"/>
<liasse code="HL" m1="000000000440754" m2="000000000401832"/>
<liasse code="HM" m1="000000000423188" m2="000000000427405"/>
<liasse code="HN" m1="000000000017566" m2="-000000000025573"/>
</page>
<page numero="05">
<liasse code="KD" m1="000000000118830"/>
<liasse code="LN" m1="000000000029041"/>
<liasse code="0G" m1="000000000147871"/>
<liasse code="IO" m3="000000000118830"/>
<liasse code="IY" m2="000000000000800" m3="000000000028241"/>
<liasse code="I4" m2="000000000000800" m3="000000000147071"/>
</page>
<page numero="06">
<liasse code="PE" m1="000000000002830" m4="000000000002830"/>
<liasse code="QU" m1="000000000026028" m2="000000000001145" m3="000000000000800" m4="000000000026373"/>
<liasse code="0N" m1="000000000028858" m2="000000000001145" m3="000000000000800" m4="000000000029203"/>
</page>
<page numero="08">
<liasse code="UX" m1="000000000054050" m2="000000000054050"/>
<liasse code="VM" m1="000000000004180" m2="000000000004180"/>
<liasse code="VB" m1="000000000005506" m2="000000000005506"/>
<liasse code="VR" m1="000000000036912" m2="000000000036912"/>
<liasse code="VS" m1="000000000002073" m2="000000000002073"/>
<liasse code="VT" m1="000000000102721" m2="000000000102721"/>
<liasse code="VG" m1="000000000030994" m2="000000000030994"/>
<liasse code="8A" m1="000000000050000" m3="000000000050000"/>
<liasse code="8B" m1="000000000057788" m2="000000000057788"/>
<liasse code="8C" m1="000000000003875" m2="000000000003875"/>
<liasse code="8D" m1="000000000008298" m2="000000000008298"/>
<liasse code="VW" m1="000000000005217" m2="000000000005217"/>
<liasse code="VQ" m1="000000000000039" m2="000000000000039"/>
<liasse code="VI" m1="000000000033277" m2="000000000033277"/>
<liasse code="8K" m1="000000000003514" m2="000000000003514"/>
<liasse code="VY" m1="000000000193002" m2="000000000143002" m3="000000000050000"/>
<liasse code="VK" m1="000000000003863"/>
</page>
</detail>
</bilan>
</bilans>
