<?xml version="1.0" encoding="UTF-8" standalone="no"?>
<bilans version="1.0" xmlns="fr:inpi:odrncs:bilansSaisisXML">
<bilan>
<identite>
<siren>413119496</siren>
<date_cloture_exercice>20181231</date_cloture_exercice>
<code_greffe>3102</code_greffe>
<num_depot>B2019/005678</num_depot>
<num_gestion>1997B01405</num_gestion>
<code_activite>4781Z</code_activite>
<date_cloture_exercice_n-1>20171231</date_cloture_exercice_n-1>
<duree_exercice_n>12</duree_exercice_n>
<duree_exercice_n-1>12</duree_exercice_n-1>
<date_depot>20190320</date_depot>
<code_motif>00</code_motif>
<code_type_bilan>C</code_type_bilan>
<code_devise>EUR</code_devise>
<code_origine_devise>O</code_origine_devise>
<code_confidentialite>0</code_confidentialite>
<info_traitement/>
<denomination><![CDATA[SARL TOULOUSE FRAIS]]></denomination>
<adresse><![CDATA[31200 TOULOUSE]]></adresse>
</identite>
<detail>
<page numero="01">
<liasse code="AH" m1="000000000047452" m3="000000000047452"/>
<liasse code="AJ" m1="000000000008102" m2="000000000008102"/>
<liasse code="AR" m1="000000000000550" m2="000000000000550"/>
<liasse code="AT" m1="000000000026080" m2="000000000019936" m3="000000000006144"/>
<liasse code="BD" m1="000000000000057" m3="000000000000057"/>
<liasse code="BH" m1="000000000001345" m3="000000000001345"/>
<liasse code="BJ" m1="000000000083586" m2="000000000028588" m3="000000000054998"/>
<liasse code="BL" m1="000000000000250" m3="000000000000250"/>
<liasse code="BT" m1="000000000008736" m3="000000000008736"/>
<liasse code="BV" m1="000000000000014" m3="000000000000014"/>
<liasse code="BX" m1="000000000137056" m2="000000000006740" m3="000000000130316"/>
<liasse code="BZ" m1="000000000011499" m3="000000000011499"/>
<liasse code="CD" m1="000000000033006" m3="000000000033006"/>
<liasse code="CF" m1="000000000039717" m3="000000000039717"/>
<liasse code="CH" m1="000000000002645" m3="000000000002645"/>
<liasse code="CJ" m1="000000000232922" m2="000000000006740" m3="000000000226182"/>
<liasse code="CO" m1="000000000316508" m2="000000000035328" m3="000000000281180"/>
</page>
<page numero="02">
<liasse code="DA" m1="000000000005400"/>
<liasse code="DB" m1="000000000000135"/>
<liasse code="DD" m1="000000000000900"/>
<liasse code="DG" m1="000000000117779"/>
<liasse code="DI" m1="000000000012374"/>
<liasse code="DL" m1="000000000136588"/>
<liasse code="DW" m1="000000000000010"/>
<liasse code="DX" m1="000000000111965"/>
<liasse code="DY" m1="000000000032617"/>
<liasse code="EC" m1="000000000144592"/>
<liasse code="EE" m1="000000000281180"/>
<liasse code="EG" m1="000000000144582"/>
</page>
<page numero="03">
<liasse code="FA" m1="000000001492851" m3="000000001492851"/>
<liasse code="FJ" m1="000000001492851" m3="000000001492851"/>
<liasse code="FP" m3="000000000007983"/>
<liasse code="FQ" m3="000000000000004"/>
<liasse code="FR" m3="000000001500838"/>
<liasse code="FS" m3="000000001131968"/>
<liasse code="FT" m3="000000000000543"/>
<liasse code="FU" m3="000000000000110"/>
<liasse code="FV" m3="000000000000050"/>
<liasse code="FW" m3="000000000130016"/>
<liasse code="FX" m3="000000000007534"/>
<liasse code="FY" m3="000000000159780"/>
<liasse code="FZ" m3="000000000050082"/>
<liasse code="GA" m3="000000000002169"/>
<liasse code="GC" m3="000000000004379"/>
<liasse code="GE" m3="000000000003654"/>
<liasse code="GF" m3="000000001490285"/>
<liasse code="GG" m3="000000000010553"/>
<liasse code="GL" m3="000000000000159"/>
<liasse code="GP" m3="000000000000159"/>
<liasse code="GR" m3="000000000000055"/>
<liasse code="GU" m3="000000000000055"/>
<liasse code="GV" m3="000000000000104"/>
<liasse code="GW" m3="000000000010657"/>
</page>
<page numero="04">
<liasse code="HA" m1="000000000001850"/>
<liasse code="HD" m1="000000000001850"/>
<liasse code="HI" m1="000000000001850"/>
<liasse code="HK" m1="000000000000133"/>
<liasse code="HL" m1="000000001502847"/>
<liasse code="HM" m1="000000001490472"/>
<liasse code="HN" m1="000000000012374"/>
</page>
<page numero="05">
<liasse code="KD" m1="000000000055554"/>
<liasse code="LN" m1="000000000026630"/>
<liasse code="LQ" m1="000000000001402"/>
<liasse code="0G" m1="000000000083586"/>
<liasse code="IO" m3="000000000055554"/>
<liasse code="IY" m3="000000000026630"/>
<liasse code="I3" m3="000000000001402"/>
<liasse code="I4" m3="000000000083586"/>
</page>
<page numero="06">
<liasse code="PE" m1="000000000008102" m4="000000000008102"/>
<liasse code="QU" m1="000000000018317" m2="000000000002169" m4="000000000020486"/>
<liasse code="0N" m1="000000000026419" m2="000000000002169" m4="000000000028588"/>
</page>
<page numero="07">
<liasse code="6T" m1="000000000010344" m2="000000000004379" m3="000000000007983" m4="000000000006740"/>
<liasse code="7B" m1="000000000010344" m2="000000000004379" m3="000000000007983" m4="000000000006740"/>
<liasse code="7C" m1="000000000010344" m2="000000000004379" m3="000000000007983" m4="000000000006740"/>
<liasse code="UE" m2="000000000004379" m3="000000000007983"/>
</page>
<page numero="08">
<liasse code="UT" m1="000000000001345" m3="000000000001345"/>
<liasse code="VA" m1="000000000008262" m2="000000000008262"/>
<liasse code="UX" m1="000000000128794" m2="000000000128794"/>
<liasse code="UZ" m1="000000000000921" m2="000000000000921"/>
<liasse code="VM" m1="000000000006088" m2="000000000006088"/>
<liasse code="VB" m1="000000000004385" m2="000000000004385"/>
<liasse code="VR" m1="000000000000106" m2="000000000000106"/>
<liasse code="VS" m1="000000000002645" m2="000000000002645"/>
<liasse code="VT" m1="000000000152545" m2="000000000151199" m3="000000000001345"/>
<liasse code="8B" m1="000000000111965" m2="000000000111965"/>
<liasse code="8C" m1="000000000007853" m2="000000000007853"/>
<liasse code="8D" m1="000000000021838" m2="000000000021838"/>
<liasse code="VW" m1="000000000000108" m2="000000000000108"/>
<liasse code="VQ" m1="000000000002818" m2="000000000002818"/>
<liasse code="VY" m1="000000000144582" m2="000000000144582"/>
</page>
<page numero="11">
<liasse code="ZE" m1="000000000020000"/>
<liasse code="XQ" m1="000000000056558"/>
<liasse code="YU" m1="000000000006166"/>
<liasse code="SS" m1="000000000010727"/>
<liasse code="ST" m1="000000000056564"/>
<liasse code="ZJ" m1="000000000130016"/>
<liasse code="YW" m1="000000000004295"/>
<liasse code="9Z" m1="000000000003239"/>
<liasse code="YX" m1="000000000007534"/>
<liasse code="YY" m1="000000000085179"/>
<liasse code="YZ" m1="000000000084604"/>
</page>
<page numero="16">
<liasse code="YP" m1="000000000000004"/>
</page>
</detail>
</bilan>
</bilans>
